COPYING
MANIFEST.in
README.rst
setup.cfg
setup.py
weakref_property.py
weakref_property.egg-info/PKG-INFO
weakref_property.egg-info/SOURCES.txt
weakref_property.egg-info/dependency_links.txt
weakref_property.egg-info/top_level.txt
weakref_property.egg-info/zip-safe