Metadata-Version: 1.0
Name: weakref-property
Version: 0.1
Summary: A Descriptor class implementing weakref properties in Python
Home-page: https://github.com/popotam/python-weakref-property
Author: Paweł Sobkowiak
Author-email: pawel.sobkowiak@gmail.com
License: GPLv3
Keywords: weakref,property,descriptor
Platform: UNKNOWN
